setup.py
crash/__init__.py
crash/admin.py
crash/api_views.py
crash/models.py
crash/serializers.py
crash/tests.py
crash/urls.py
crash/views.py
crash/migrations/__init__.py
crash/test_data/__init__.py
crash/test_data/crash.py
log_collection/__init__.py
log_collection/settings.py
log_collection/urls.py
log_collection/wsgi.py
mobilecrash.egg-info/PKG-INFO
mobilecrash.egg-info/SOURCES.txt
mobilecrash.egg-info/dependency_links.txt
mobilecrash.egg-info/requires.txt
mobilecrash.egg-info/top_level.txt