Metadata-Version: 1.0
Name: mobilecrash
Version: 0.0.1
Summary: crash log collection
Home-page: UNKNOWN
Author: ck
Author-email: ck@all.com
License: MIT License
Keywords: crash
Platform: any
